Metadata-Version: 2.0
Name: django-mfa2
Version: 1.1
Summary: Allows user to add 2FA to their accounts
Home-page: https://github.com/mkalioby/django-mfa2/
Author: Mohamed El-Kalioby
Author-email: mkalioby@mkalioby.com
License: MIT
Download-URL: https://github.com/mkalioby/django-mfa2/
Platform: UNKNOWN
Classifier: Development Status :: 5 - Production/Stable
Classifier: Environment :: Web Environment
Classifier: Framework :: Django
Classifier: Framework :: Django :: 1.7
Classifier: Framework :: Django :: 1.8
Classifier: Framework :: Django :: 1.9
Classifier: Framework :: Django :: 1.10
Classifier: Framework :: Django :: 1.11
Classifier: Framework :: Django :: 2.0
Classifier: Framework :: Django :: 2.1
Classifier: Intended Audience :: Developers
Classifier: Operating System :: OS Independent
Classifier: Programming Language :: Python
Classifier: Programming Language :: Python :: 2
Classifier: Programming Language :: Python :: 2.7
Classifier: Programming Language :: Python :: 3
Classifier: Programming Language :: Python :: 3.4
Classifier: Programming Language :: Python :: 3.5
Classifier: Programming Language :: Python :: 3.6
Classifier: Topic :: Software Development :: Libraries :: Python Modules
Requires-Python: >=2.7, !=3.0.*, !=3.1.*, !=3.2.*, !=3.3.*
Requires-Dist: django (>=1.7)
Requires-Dist: fido2 (==0.5)
Requires-Dist: jsonLookup
Requires-Dist: jsonfield
Requires-Dist: pyotp
Requires-Dist: python-jose
Requires-Dist: python-u2flib-server
Requires-Dist: simplejson
Requires-Dist: ua-parser
Requires-Dist: user-agents
